src/const.py
src/main.py
src/message.py
src/order.py
src/order_pool.py
src/reader.py
src/wrapper.py
fix_wrapper-1.0.dist-info/METADATA
fix_wrapper-1.0.dist-info/WHEEL
fix_wrapper-1.0.dist-info/top_level.txt
fix_wrapper-1.0.dist-info/RECORD
